instamatic/__init__.py
instamatic/_collections.py
instamatic/_typing.py
instamatic/acquire_at_items.py
instamatic/admin.py
instamatic/banner.py
instamatic/browser.py
instamatic/controller.py
instamatic/exceptions.py
instamatic/goniotool.py
instamatic/gridmontage.py
instamatic/image_utils.py
instamatic/imreg.py
instamatic/io.py
instamatic/main.py
instamatic/montage.py
instamatic/tools.py
instamatic/camera/CCDCOM.h
instamatic/camera/CCDCOM2_x64_gatan.dll
instamatic/camera/CCDCOM2_x64_simulation.dll
instamatic/camera/CCDCOM2_x86_gatan.dll
instamatic/camera/CCDCOM2_x86_simulation.dll
instamatic/camera/EMCameraObj.dll
instamatic/camera/gatansocket3.md
instamatic/camera/mpxhwrelaxd.dll
instamatic/camera/timepix.lockfile
instamatic/camera/tpx/171207_with_flatfield.bpc
instamatic/camera/tpx/171207_with_flatfield.bpc.dacs
instamatic/camera/tpx/HW.dacs
instamatic/camera/tpx/config.txt
instamatic/config/defaults.yaml
instamatic/config/settings.yaml
instamatic/config/alignments/neutral.yaml
instamatic/config/calibration/orius.yaml
instamatic/config/calibration/simulate.yaml
instamatic/config/calibration/timepix.yaml
instamatic/config/calibration/tvips-f416.yaml
instamatic/config/camera/merlin.yaml
instamatic/config/camera/orius.yaml
instamatic/config/camera/serval.yaml
instamatic/config/camera/simulate.yaml
instamatic/config/camera/simulateDLL.yaml
instamatic/config/camera/timepix.yaml
instamatic/config/camera/tvips-f416.yaml
instamatic/config/camera/tvips-xf416.yaml
instamatic/config/microscope/fei_simu.yaml
instamatic/config/microscope/fei_themisZ.yaml
instamatic/config/microscope/jeol-1400.yaml
instamatic/config/microscope/jeol.yaml
instamatic/config/microscope/simulate.yaml
instamatic/config/scripts/readme.md
instamatic/neural_network/weights-py2.p
instamatic/neural_network/weights-py3.p
instamatic/processing/PETS_input_keywords.csv
instamatic-2.2.0.dist-info/licenses/LICENCE
instamatic-2.2.0.dist-info/METADATA
instamatic-2.2.0.dist-info/WHEEL
instamatic-2.2.0.dist-info/entry_points.txt
instamatic-2.2.0.dist-info/top_level.txt
instamatic-2.2.0.dist-info/RECORD
