Metadata-Version: 2.4
Name: instamatic
Version: 2.2.0
Summary: Python program for automated electron diffraction data collection
Author-email: Stef Smeets <s.smeets@esciencecenter.nl>
Maintainer-email: Daniel Mariusz Tchoń <tchon@fzu.cz>
License: BSD License
Project-URL: homepage, https://github.com/instamatic-dev/instamatic
Project-URL: issues, http://github.com/instamatic-dev/instamatic/issues
Project-URL: documentation, https://instamatic.readthedocs.io
Project-URL: changelog, https://github.com/instamatic-dev/instamatic/releases
Keywords: electron-crystallography,electron-microscopy,electron-diffraction,serial-crystallography,3D-electron-diffraction,micro-ed,data-collection,automation
Classifier: Programming Language :: Python :: 3.9
Classifier: Programming Language :: Python :: 3.10
Classifier: Programming Language :: Python :: 3.11
Classifier: Programming Language :: Python :: 3.12
Classifier: Programming Language :: Python :: 3.13
Classifier: Development Status :: 5 - Production/Stable
Classifier: Intended Audience :: Science/Research
Classifier: License :: OSI Approved :: BSD License
Classifier: Operating System :: Microsoft :: Windows
Classifier: Topic :: Scientific/Engineering :: Human Machine Interfaces
Classifier: Topic :: Scientific/Engineering :: Chemistry
Classifier: Topic :: Software Development :: Libraries
Requires-Python: >=3.9
License-File: LICENCE
Requires-Dist: comtypes>=1.1.7; sys_platform == "win32"
Requires-Dist: h5py>=2.10.0
Requires-Dist: ipython>=7.11.1
Requires-Dist: lmfit>=1.0.0
Requires-Dist: matplotlib>=3.1.2
Requires-Dist: mrcfile>=1.1.2
Requires-Dist: numpy>=1.17.3
Requires-Dist: pandas>=1.0.0
Requires-Dist: pillow>=7.0.0
Requires-Dist: pywinauto>=0.6.8; sys_platform == "windows"
Requires-Dist: pyyaml>=5.3
Requires-Dist: scikit-image>=0.17.1
Requires-Dist: scipy>=1.3.2
Requires-Dist: tifffile>=2019.7.26.2
Requires-Dist: tqdm>=4.41.1
Requires-Dist: typing_extensions>=4.0.0
Requires-Dist: virtualbox>=2.0.0
Requires-Dist: pyserialem>=0.3.2
Requires-Dist: diffpy.structure
Provides-Extra: develop
Requires-Dist: bump-my-version; extra == "develop"
Requires-Dist: check-manifest; extra == "develop"
Requires-Dist: pre-commit; extra == "develop"
Requires-Dist: pytest>=5.4.1; extra == "develop"
Requires-Dist: coverage; extra == "develop"
Provides-Extra: serval
Requires-Dist: serval-toolkit; extra == "serval"
Provides-Extra: docs
Requires-Dist: markdown-include; extra == "docs"
Requires-Dist: mkdocs; extra == "docs"
Requires-Dist: mkdocs-jupyter; extra == "docs"
Requires-Dist: mkdocs-gen-files; extra == "docs"
Requires-Dist: mkdocs-material; extra == "docs"
Requires-Dist: mkdocstrings[python]; extra == "docs"
Provides-Extra: publishing
Requires-Dist: twine; extra == "publishing"
Requires-Dist: wheel; extra == "publishing"
Requires-Dist: build; extra == "publishing"
Dynamic: license-file
